nhl_calendar/__init__.py
nhl_calendar/output.py
nhl_calendar/queries.py
nhl_calendar/templates/index.j2.html
nhl_calendar/wsgi.py
nhl_calendar-0.1.2.dist-info/METADATA
nhl_calendar-0.1.2.dist-info/WHEEL
nhl_calendar-0.1.2.dist-info/RECORD
