Metadata-Version: 2.1
Name: nhl-calendar
Version: 0.1.2
Summary: Simple program to display the current week's games and generate iCal files to add a team's schedule to your calendar
Author: Dave Brown
Author-email: dave.brown@exit107.com
Requires-Python: >=3.10,<4.0
Classifier: Programming Language :: Python :: 3
Classifier: Programming Language :: Python :: 3.10
Classifier: Programming Language :: Python :: 3.11
Classifier: Programming Language :: Python :: 3.12
Classifier: Programming Language :: Python :: 3.13
Requires-Dist: datetype (>=2024.2.28,<2025.0.0)
Requires-Dist: flask (>=3.1.0,<4.0.0)
Requires-Dist: gunicorn (>=23.0.0,<24.0.0)
Requires-Dist: ical (>=8.2.0,<9.0.0)
Requires-Dist: python-dateutil (>=2.9.0.post0,<3.0.0)
Requires-Dist: pytz (>=2024.2,<2025.0)
Requires-Dist: requests (>=2.32.3,<3.0.0)
Requires-Dist: types-python-dateutil (>=2.9.0.20241206,<3.0.0.0)
Requires-Dist: types-pytz (>=2024.2.0.20241003,<2025.0.0.0)
Requires-Dist: types-requests (>=2.32.0.20241016,<3.0.0.0)
